extBrightness-1.0.4.dist-info/DESCRIPTION.rst
extBrightness-1.0.4.dist-info/METADATA
extBrightness-1.0.4.dist-info/RECORD
extBrightness-1.0.4.dist-info/WHEEL
extBrightness-1.0.4.dist-info/entry_points.txt
extBrightness-1.0.4.dist-info/metadata.json
extBrightness-1.0.4.dist-info/top_level.txt
src/__init__.py
src/bright.py
src/console.py
src/gui.py
src/res.py
