Metadata-Version: 2.0
Name: extBrightness
Version: 1.0.4
Summary: Extended brightness and gamma control for (external) screens on X11 systems
Home-page: http://www.toolcase.org/app/linux/extBrightness
Author: Jörg Mäder
Author-email: member@toolcase.org
License: GNU GENERAL PUBLIC LICENSE V3
Keywords: brightness gamma screen projector external multiple profile
Platform: UNKNOWN
Classifier: Development Status :: 5 - Production/Stable
Classifier: Operating System :: POSIX :: Linux
Classifier: Environment :: X11 Applications
Classifier: Intended Audience :: End Users/Desktop
Classifier: Topic :: System :: Hardware
Classifier: License :: OSI Approved :: GNU General Public License v3 (GPLv3)
Classifier: Programming Language :: Python :: 3
Classifier: Programming Language :: Python :: 3.3
Classifier: Programming Language :: Python :: 3.4
Classifier: Programming Language :: Python :: 3.5
Provides-Extra: dev
Provides-Extra: test
